power_ml/__init__.py
power_ml/ai/__init__.py
power_ml/ai/metrics.py
power_ml/ai/model.py
power_ml/ai/permutation_importance.py
power_ml/ai/predictor/__init__.py
power_ml/ai/predictor/base_predictor.py
power_ml/ai/predictor/light_gbm.py
power_ml/ai/predictor/sklearn_predictor.py
power_ml/ai/selection/__init__.py
power_ml/ai/selection/selector.py
power_ml/ai/selection/split.py
power_ml/ai/types.py
power_ml/data/__init__.py
power_ml/data/local_pickle_store.py
power_ml/data/s3_pickle_store.py
power_ml/data/store.py
power_ml/platform/catalog.py
power_ml/platform/model_flow.py
power_ml/platform/project.py
power_ml/stats/col_stats.py
power_ml/util/__init__.py
power_ml/util/dict_util.py
power_ml/util/fmt.py
power_ml/util/memory.py
power_ml/util/numeric.py
power_ml/util/seed.py
power_ml/util/timer.py
power_ml/util/version.py
power_ml-1.0.0a2.dist-info/LICENSE
power_ml-1.0.0a2.dist-info/WHEEL
power_ml-1.0.0a2.dist-info/METADATA
power_ml-1.0.0a2.dist-info/RECORD
